Workbook

Sheet Mode d'emploi
B1: Saisie des prix de vente
B2: Comptoir des Chatonniers — 702 produits issus de la base fournisseurs 2026
B4: Nouveau : les prix sont préremplis
B5: Les 701 prix de vente proposés par coefficients de marché sont déjà dans la colonne PRIX DE VENTE HT, avec le statut PROPOSÉ. Votre travail n'est plus de saisir 700 prix : c'est de les relire, corriger ceux qui tombent à côté, et passer le statut à VALIDÉ. Un prix non validé reste une hypothèse de travail.
B7: Ce qu'il faut remplir
B8: Trois colonnes seulement, surlignées en jaune dans l'onglet « Prix de vente » :
B9: • PRIX DE VENTE HT — le prix auquel vous vendez le produit dans un coffret.
B10: • CATALOGUE SAISON — OUI si vous retenez le produit pour la saison en cours.
B11: • NOTES — vos remarques (produit à revoir, fournisseur à rappeler…).
B12: Tout le reste est calculé automatiquement : marge, taux de marge, coefficient, prix TTC.
B14: Ne saisissez pas les 702 prix
B15: Commencez par le catalogue de saison : 120 à 200 références que vous savez pouvoir obtenir. Mettez OUI dans la colonne CATALOGUE SAISON, puis ne saisissez le prix que pour celles-là. Le moteur de composition n'a besoin que de produits fiables, pas de tous les produits.
... B32: Enregistrez le fichier sans changer son nom ni l'ordre des colonnes, et renvoyez-le. Il se réimporte tel quel dans la base de données.

Sheet Prix de vente
A1: ID | B1: PRODUIT | C1: CATÉGORIE | D1: SOUS-CATÉGORIE | E1: GAMME | F1: PRODUCTEUR | G1: FOURNISSEUR | H1: CONDITIONNEMENT | I1: POIDS/VOL. | J1: ALCOOL | K1: TVA | L1: PRIX ACHAT HT | M1: PRIX DE VENTE HT | N1: STATUT PRIX | O1: MARGE € | P1: TAUX DE MARGE | Q1: COEFF. | R1: PRIX VENTE TTC | S1: CATALOGUE SAISON | T1: NOTES
A2: PROD-0396 | B2: Pinte 50 cl Brasserie Lalie | C2: ART_DE_LA_TABLE_ET_OBJET | D2: OBJET_ET_CONTENANT | E2: ESSENTIEL | F2: BRASSERIE LA LIE | G2: NORMAND DIRECT TERROIR | I2: 500 ml | J2: NON | K2: 20 % | L2: 2.38 | M2: 6 | N2: PROPOSÉ | O2: =IF(M2="","",M2-L2) | P2: =IF(OR(M2="",M2=0),"",(M2-L2)/M2) | Q2: =IF(OR(M2="",L2=0,L2=""),"",M2/L2) | R2: =IF(M2="","",M2*1.2)
A3: PROD-0397 | B3: Verre à bière Brasserie Lalie 25 cl | C3: ART_DE_LA_TABLE_ET_OBJET | D3: OBJET_ET_CONTENANT | E3: ESSENTIEL | F3: BRASSERIE LA LIE | G3: NORMAND DIRECT TERROIR | I3: 250 ml | J3: NON | K3: 20 % | L3: 2.1 | M3: 5.3 | N3: PROPOSÉ | O3: =IF(M3="","",M3-L3) | P3: =IF(OR(M3="",M3=0),"",(M3-L3)/M3) | Q3: =IF(OR(M3="",L3=0,L3=""),"",M3/L3) | R3: =IF(M3="","",M3*1.2)
A4: PROD-0657 | B4: PRÉSENTOIR POUR 100 SUCETTES | C4: ART_DE_LA_TABLE_ET_OBJET | D4: OBJET_ET_CONTENANT | E4: SIGNATURE | F4: CARAMELS D'ISIGNY | G4: CARAMELS D'ISIGNY | H4: 225G | I4: 225 g | J4: NON | K4: 20 % | L4: 8.38 | M4: 17.7 | N4: PROPOSÉ | O4: =IF(M4="","",M4-L4) | P4: =IF(OR(M4="",M4=0),"",(M4-L4)/M4) | Q4: =IF(OR(M4="",L4=0,L4=""),"",M4/L4) | R4: =IF(M4="","",M4*1.2)
A5: PROD-0018 | B5: Financiers boite 250 grs | C5: BISCUITERIE | D5: BISCUIT | E5: ESSENTIEL | F5: BISCUITERIE DE QUINEVILLE | G5: NORMAND DIRECT TERROIR | I5: 250 g | J5: NON | K5: 5.5 % | L5: 4.9 | M5: 11.8 | N5: PROPOSÉ | O5: =IF(M5="","",M5-L5) | P5: =IF(OR(M5="",M5=0),"",(M5-L5)/M5) | Q5: =IF(OR(M5="",L5=0,L5=""),"",M5/L5) | R5: =IF(M5="","",M5*1.055)
A6: PROD-0013 | B6: Croquenoisette chocolat 180 grs | C6: BISCUITERIE | D6: BISCUIT | E6: ESSENTIEL | F6: BISCUITERIE DE QUINEVILLE | G6: NORMAND DIRECT TERROIR | I6: 180 g | J6: NON | K6: 5.5 % | L6: 4.55 | M6: 10.9 | N6: PROPOSÉ | O6: =IF(M6="","",M6-L6) | P6: =IF(OR(M6="",M6=0),"",(M6-L6)/M6) | Q6: =IF(OR(M6="",L6=0,L6=""),"",M6/L6) | R6: =IF(M6="","",M6*1.055)
A7: PROD-0020 | B7: Sablé chocolat enrobage chocolat lait 180 grs | C7: BISCUITERIE | D7: BISCUIT | E7: ESSENTIEL | F7: BISCUITERIE DE QUINEVILLE | G7: NORMAND DIRECT TERROIR | I7: 180 g | J7: NON | K7: 5.5 % | L7: 4.5 | M7: 10.8 | N7: PROPOSÉ | O7: =IF(M7="","",M7-L7) | P7: =IF(OR(M7="",M7=0),"",(M7-L7)/M7) | Q7: =IF(OR(M7="",L7=0,L7=""),"",M7/L7) | R7: =IF(M7="","",M7*1.055)
A8: PROD-0008 | B8: Coquilles Quinéville 165 grs | C8: BISCUITERIE | D8: BISCUIT | E8: ESSENTIEL | F8: BISCUITERIE DE QUINEVILLE | G8: NORMAND DIRECT TERROIR | I8: 165 g | J8: NON | K8: 5.5 % | L8: 4.37 | M8: 10.5 | N8: PROPOSÉ | O8: =IF(M8="","",M8-L8) | P8: =IF(OR(M8="",M8=0),"",(M8-L8)/M8) | Q8: =IF(OR(M8="",L8=0,L8=""),"",M8/L8) | R8: =IF(M8="","",M8*1.055)
A9: PROD-0010 | B9: Coquilles de Quinéville trio 165 grs | C9: BISCUITERIE | D9: BISCUIT | E9: ESSENTIEL | F9: BISCUITERIE DE QUINEVILLE | G9: NORMAND DIRECT TERROIR | I9: 165 g | J9: NON | K9: 5.5 % | L9: 4.37 | M9: 10.5 | N9: PROPOSÉ | O9: =IF(M9="","",M9-L9) | P9: =IF(OR(M9="",M9=0),"",(M9-L9)/M9) | Q9: =IF(OR(M9="",L9=0,L9=""),"",M9/L9) | R9: =IF(M9="","",M9*1.055)
A10: PROD-0012 | B10: Croquant aux amandes 125 grs | C10: BISCUITERIE | D10: BISCUIT | E10: ESSENTIEL | F10: BISCUITERIE DE QUINEVILLE | G10: NORMAND DIRECT TERROIR | I10: 125 g | J10: NON | K10: 5.5 % | L10: 4.3 | M10: 10.3 | N10: PROPOSÉ | O10: =IF(M10="","",M10-L10) | P10: =IF(OR(M10="",M10=0),"",(M10-L10)/M10) | Q10: =IF(OR(M10="",L10=0,L10=""),"",M10/L10) | R10: =IF(M10="","",M10*1.055)
A11: PROD-0658 | B11: COOKIES AUX ÉCLATS DE CARAMEL | C11: BISCUITERIE | D11: BISCUIT | E11: ESSENTIEL | F11: CARAMELS D'ISIGNY | G11: CARAMELS D'ISIGNY | H11: 220G | I11: 220 g | J11: NON | K11: 5.5 % | L11: 4.16 | M11: 10 | N11: PROPOSÉ | O11: =IF(M11="","",M11-L11) | P11: =IF(OR(M11="",M11=0),"",(M11-L11)/M11) | Q11: =IF(OR(M11="",L11=0,L11=""),"",M11/L11) | R11: =IF(M11="","",M11*1.055)
A12: PROD-0023 | B12: Sablé spéculos 250 grs | C12: BISCUITERIE | D12: BISCUIT | E12: ESSENTIEL | F12: BISCUITERIE DE QUINEVILLE | G12: NORMAND DIRECT TERROIR | I12: 250 g | J12: NON | K12: 5.5 % | L12: 3.95 | M12: 9.5 | N12: PROPOSÉ | O12: =IF(M12="","",M12-L12) | P12: =IF(OR(M12="",M12=0),"",(M12-L12)/M12) | Q12: =IF(OR(M12="",L12=0,L12=""),"",M12/L12) | R12: =IF(M12="","",M12*1.055)
A13: PROD-0454 | B13: Pain D'épices aux pépites de Chocolats 250gr | C13: BISCUITERIE | D13: BISCUIT | E13: ESSENTIEL | F13: Rucher du bocage Virois | G13: NORMAND DIRECT TERROIR | H13: Barquette en bois | I13: 250 g | J13: NON | K13: 5.5 % | L13: 3.95 | M13: 9.5 | N13: PROPOSÉ | O13: =IF(M13="","",M13-L13) | P13: =IF(OR(M13="",M13=0),"",(M13-L13)/M13) | Q13: =IF(OR(M13="",L13=0,L13=""),"",M13/L13) | R13: =IF(M13="","",M13*1.055)
A14: PROD-0455 | B14: Pain D'épices aux éclats de Noix 250gr | C14: BISCUITERIE | D14: BISCUIT | E14: ESSENTIEL | F14: Rucher du bocage Virois | G14: NORMAND DIRECT TERROIR | H14: Barquette en bois | I14: 250 g | J14: NON | K14: 5.5 % | L14: 3.95 | M14: 9.5 | N14: PROPOSÉ | O14: =IF(M14="","",M14-L14) | P14: =IF(OR(M14="",M14=0),"",(M14-L14)/M14) | Q14: =IF(OR(M14="",L14=0,L14=""),"",M14/L14) | R14: =IF(M14="","",M14*1.055)
A15: PROD-0456 | B15: Pain D'épices aux écorces d'Oranges 250gr | C15: BISCUITERIE | D15: BISCUIT | E15: ESSENTIEL | F15: Rucher du bocage Virois | G15: NORMAND DIRECT TERROIR | H15: Barquette en bois | I15: 250 g | J15: NON | K15: 5.5 % | L15: 3.95 | M15: 9.5 | N15: PROPOSÉ | O15: =IF(M15="","",M15-L15) | P15: =IF(OR(M15="",M15=0),"",(M15-L15)/M15) | Q15: =IF(OR(M15="",L15=0,L15=""),"",M15/L15) | R15: =IF(M15="","",M15*1.055)
A16: PROD-0457 | B16: Pain D'épices aux Figues 250gr (fin d'année) | C16: BISCUITERIE | D16: BISCUIT | E16: ESSENTIEL | F16: Rucher du bocage Virois | G16: NORMAND DIRECT TERROIR | H16: Barquette en bois | I16: 250 g | J16: NON | K16: 5.5 % | L16: 3.95 | M16: 9.5 | N16: PROPOSÉ | O16: =IF(M16="","",M16-L16) | P16: =IF(OR(M16="",M16=0),"",(M16-L16)/M16) | Q16: =IF(OR(M16="",L16=0,L16=""),"",M16/L16) | R16: =IF(M16="","",M16*1.055)
A17: PROD-0025 | B17: Tuiles pâtissières 150 grs | C17: BISCUITERIE | D17: BISCUIT | E17: ESSENTIEL | F17: BISCUITERIE DE QUINEVILLE | G17: NORMAND DIRECT TERROIR | I17: 150 g | J17: NON | K17: 5.5 % | L17: 3.85 | M17: 9.2 | N17: PROPOSÉ | O17: =IF(M17="","",M17-L17) | P17: =IF(OR(M17="",M17=0),"",(M17-L17)/M17) | Q17: =IF(OR(M17="",L17=0,L17=""),"",M17/L17) | R17: =IF(M17="","",M17*1.055)
A18: PROD-0453 | B18: Pain D'épices Nature 250gr | C18: BISCUITERIE | D18: BISCUIT | E18: ESSENTIEL | F18: Rucher du bocage Virois | G18: NORMAND DIRECT TERROIR | H18: Barquette en bois | I18: 250 g | J18: NON | K18: 5.5 % | L18: 3.8 | M18: 9.1 | N18: PROPOSÉ | O18: =IF(M18="","",M18-L18) | P18: =IF(OR(M18="",M18=0),"",(M18-L18)/M18) | Q18: =IF(OR(M18="",L18=0,L18=""),"",M18/L18) | R18: =IF(M18="","",M18*1.055)
A19: PROD-0014 | B19: Croquenoisettes 180 grs | C19: BISCUITERIE | D19: BISCUIT | E19: ESSENTIEL | F19: BISCUITERIE DE QUINEVILLE | G19: NORMAND DIRECT TERROIR | I19: 180 g | J19: NON | K19: 5.5 % | L19: 3.73 | M19: 9 | N19: PROPOSÉ | O19: =IF(M19="","",M19-L19) | P19: =IF(OR(M19="",M19=0),"",(M19-L19)/M19) | Q19: =IF(OR(M19="",L19=0,L19=""),"",M19/L19) | R19: =IF(M19="","",M19*1.055)
A20: PROD-0024 | B20: Sablés Mamie 220 grs | C20: BISCUITERIE | D20: BISCUIT | E20: ESSENTIEL | F20: BISCUITERIE DE QUINEVILLE | G20: NORMAND DIRECT TERROIR | I20: 220 g | J20: NON | K20: 5.5 % | L20: 3.65 | M20: 8.8 | N20: PROPOSÉ | O20: =IF(M20="","",M20-L20) | P20: =IF(OR(M20="",M20=0),"",(M20-L20)/M20) | Q20: =IF(OR(M20="",L20=0,L20=""),"",M20/L20) | R20: =IF(M20="","",M20*1.055)
A21: PROD-0005 | B21: Boutons de la Manche 250 grs moins de 12 | C21: BISCUITERIE | D21: BISCUIT | E21: ESSENTIEL | F21: BISCUITERIE DE QUINEVILLE | G21: NORMAND DIRECT TERROIR | I21: 250 g | J21: NON | K21: 5.5 % | L21: 3.6 | M21: 8.6 | N21: PROPOSÉ | O21: =IF(M21="","",M21-L21) | P21: =IF(OR(M21="",M21=0),"",(M21-L21)/M21) | Q21: =IF(OR(M21="",L21=0,L21=""),"",M21/L21) | R21: =IF(M21="","",M21*1.055)
A22: PROD-0007 | B22: Cookies pépite de chocolat 220 grs | C22: BISCUITERIE | D22: BISCUIT | E22: ESSENTIEL | F22: BISCUITERIE DE QUINEVILLE | G22: NORMAND DIRECT TERROIR | I22: 220 g | J22: NON | K22: 5.5 % | L22: 3.6 | M22: 8.6 | N22: PROPOSÉ | O22: =IF(M22="","",M22-L22) | P22: =IF(OR(M22="",M22=0),"",(M22-L22)/M22) | Q22: =IF(OR(M22="",L22=0,L22=""),"",M22/L22) | R22: =IF(M22="","",M22*1.055)
A23: PROD-0021 | B23: Sablé éclats de caramel 180 grs | C23: BISCUITERIE | D23: BISCUIT | E23: ESSENTIEL | F23: BISCUITERIE DE QUINEVILLE | G23: NORMAND DIRECT TERROIR | I23: 180 g | J23: NON | K23: 5.5 % | L23: 3.56 | M23: 8.5 | N23: PROPOSÉ | O23: =IF(M23="","",M23-L23) | P23: =IF(OR(M23="",M23=0),"",(M23-L23)/M23) | Q23: =IF(OR(M23="",L23=0,L23=""),"",M23/L23) | R23: =IF(M23="","",M23*1.055)
A24: PROD-0016 | B24: Croquet Calvados 180 grs | C24: BISCUITERIE | D24: BISCUIT | E24: ESSENTIEL | F24: BISCUITERIE DE QUINEVILLE | G24: NORMAND DIRECT TERROIR | I24: 180 g | J24: INGREDIENT_ALCOOLISE | K24: 5.5 % | L24: 3.55 | M24: 8.5 | N24: PROPOSÉ | O24: =IF(M24="","",M24-L24) | P24: =IF(OR(M24="",M24=0),"",(M24-L24)/M24) | Q24: =IF(OR(M24="",L24=0,L24=""),"",M24/L24) | R24: =IF(M24="","",M24*1.055)
A25: PROD-0015 | B25: Croquentin 220 grs | C25: BISCUITERIE | D25: BISCUIT | E25: ESSENTIEL | F25: BISCUITERIE DE QUINEVILLE | G25: NORMAND DIRECT TERROIR | I25: 220 g | J25: NON | K25: 5.5 % | L25: 3.5 | M25: 8.4 | N25: PROPOSÉ | O25: =IF(M25="","",M25-L25) | P25: =IF(OR(M25="",M25=0),"",(M25-L25)/M25) | Q25: =IF(OR(M25="",L25=0,L25=""),"",M25/L25) | R25: =IF(M25="","",M25*1.055)
A26: PROD-0006 | B26: Boutons de la Manche 250 grs/ carton de 12 | C26: BISCUITERIE | D26: BISCUIT | E26: ESSENTIEL | F26: BISCUITERIE DE QUINEVILLE | G26: NORMAND DIRECT TERROIR | I26: 250 g | J26: NON | K26: 5.5 % | L26: 3.45 | M26: 8.3 | N26: PROPOSÉ | O26: =IF(M26="","",M26-L26) | P26: =IF(OR(M26="",M26=0),"",(M26-L26)/M26) | Q26: =IF(OR(M26="",L26=0,L26=""),"",M26/L26) | R26: =IF(M26="","",M26*1.055)
A27: PROD-0019 | B27: Pailles feuilletées au sucre 150 grs | C27: BISCUITERIE | D27: BISCUIT | E27: ESSENTIEL | F27: BISCUITERIE DE QUINEVILLE | G27: NORMAND DIRECT TERROIR | I27: 150 g | J27: NON | K27: 5.5 % | L27: 3.45 | M27: 8.3 | N27: PROPOSÉ | O27: =IF(M27="","",M27-L27) | P27: =IF(OR(M27="",M27=0),"",(M27-L27)/M27) | Q27: =IF(OR(M27="",L27=0,L27=""),"",M27/L27) | R27: =IF(M27="","",M27*1.055)
A28: PROD-0017 | B28: Financier sachet 180 grs | C28: BISCUITERIE | D28: BISCUIT | E28: ESSENTIEL | F28: BISCUITERIE DE QUINEVILLE | G28: NORMAND DIRECT TERROIR | I28: 180 g | J28: NON | K28: 5.5 % | L28: 3.25 | M28: 7.8 | N28: PROPOSÉ | O28: =IF(M28="","",M28-L28) | P28: =IF(OR(M28="",M28=0),"",(M28-L28)/M28) | Q28: =IF(OR(M28="",L28=0,L28=""),"",M28/L28) | R28: =IF(M28="","",M28*1.055)
A29: PROD-0026 | B29: Sablette mendiante chocolat 130 grs | C29: BISCUITERIE | D29: BISCUIT | E29: ESSENTIEL | F29: BISCUITERIE DE QUINEVILLE | G29: NORMAND DIRECT TERROIR | I29: 130 g | J29: NON | K29: 5.5 % | L29: 3 | M29: 7.2 | N29: PROPOSÉ | O29: =IF(M29="","",M29-L29) | P29: =IF(OR(M29="",M29=0),"",(M29-L29)/M29) | Q29: =IF(OR(M29="",L29=0,L29=""),"",M29/L29) | R29: =IF(M29="","",M29*1.055)
A30: PROD-0003 | B30: Palets Camembert du Cotentin pavot 100 grs | C30: BISCUITERIE | D30: BISCUIT | E30: ESSENTIEL | F30: BISCUITERIE DE QUINEVILLE | G30: NORMAND DIRECT TERROIR | I30: 100 g | J30: NON | K30: 5.5 % | L30: 2.5 | M30: 6.6 | N30: PROPOSÉ | O30: =IF(M30="","",M30-L30) | P30: =IF(OR(M30="",M30=0),"",(M30-L30)/M30) | Q30: =IF(OR(M30="",L30=0,L30=""),"",M30/L30) | R30: =IF(M30="","",M30*1.055)
... A35: PROD-0001 | B35: Apéro tomate/paprika 100 grs | C35: BISCUITERIE | D35: BISCUIT | E35: ESSENTIEL | F35: BISCUITERIE DE QUINEVILLE | G35: NORMAND DIRECT TERROIR | I35: 100 g | J35: NON | K35: 5.5 % | L35: 2.15 | M35: 5.7 | N35: PROPOSÉ | O35: =IF(M35="","",M35-L35) | P35: =IF(OR(M35="",M35=0),"",(M35-L35)/M35) | Q35: =IF(OR(M35="",L35=0,L35=""),"",M35/L35) | R35: =IF(M35="","",M35*1.055)
A36: PROD-0452 | B36: Pain D'épices Nature 100gr | C36: BISCUITERIE | D36: BISCUIT | E36: ESSENTIEL | F36: Rucher du bocage Virois | G36: NORMAND DIRECT TERROIR | H36: Barquette en bois | I36: 100 g | J36: NON | K36: À CONFIRMER | L36: 1.9 | M36: 5 | N36: PROPOSÉ | O36: =IF(M36="","",M36-L36) | P36: =IF(OR(M36="",M36=0),"",(M36-L36)/M36) | Q36: =IF(OR(M36="",L36=0,L36=""),"",M36/L36) | R36: =IF(M36="","","TVA à confirmer")
A37: PROD-0029 | B37: Tuiles chocolat noir et lacté 200gr | C37: BISCUITERIE | D37: BISCUIT | E37: SIGNATURE | F37: BISCUITERIE DE QUINEVILLE | G37: NORMAND DIRECT TERROIR | I37: 200 g | J37: NON | K37: 20 % | L37: 8.3 | M37: 18.3 | N37: PROPOSÉ | O37: =IF(M37="","",M37-L37) | P37: =IF(OR(M37="",M37=0),"",(M37-L37)/M37) | Q37: =IF(OR(M37="",L37=0,L37=""),"",M37/L37) | R37: =IF(M37="","",M37*1.2)
A38: PROD-0032 | B38: Grignotines amandes noisettes 200 grs | C38: BISCUITERIE | D38: BISCUIT | E38: SIGNATURE | F38: BISCUITERIE DE QUINEVILLE | G38: NORMAND DIRECT TERROIR | I38: 200 g | J38: NON | K38: 5.5 % | L38: 7.4 | M38: 17.8 | N38: PROPOSÉ | O38: =IF(M38="","",M38-L38) | P38: =IF(OR(M38="",M38=0),"",(M38-L38)/M38) | Q38: =IF(OR(M38="",L38=0,L38=""),"",M38/L38) | R38: =IF(M38="","",M38*1.055)
A39: PROD-0284 | B39: BISCUITS 150g CAEN Mairie | C39: BISCUITERIE | D39: BISCUIT | E39: SIGNATURE | F39: BALADES NORMANDES | G39: NORMAND DIRECT TERROIR | H39: Boîte fer | I39: 150 g | J39: NON | K39: 5.5 % | L39: 7.31 | M39: 17.5 | N39: PROPOSÉ | O39: =IF(M39="","",M39-L39) | P39: =IF(OR(M39="",M39=0),"",(M39-L39)/M39) | Q39: =IF(OR(M39="",L39=0,L39=""),"",M39/L39) | R39: =IF(M39="","",M39*1.055)
A40: PROD-0285 | B40: BISCUITS 150g Ouistreham B-LEC | C40: BISCUITERIE | D40: BISCUIT | E40: SIGNATURE | F40: BALADES NORMANDES | G40: NORMAND DIRECT TERROIR | H40: Boîte fer | I40: 150 g | J40: NON | K40: 5.5 % | L40: 7.31 | M40: 17.5 | N40: PROPOSÉ | O40: =IF(M40="","",M40-L40) | P40: =IF(OR(M40="",M40=0),"",(M40-L40)/M40) | Q40: =IF(OR(M40="",L40=0,L40=""),"",M40/L40) | R40: =IF(M40="","",M40*1.055)
A41: PROD-0286 | B41: BISCUITS 150g Caen Château B-LEC | C41: BISCUITERIE | D41: BISCUIT | E41: SIGNATURE | F41: BALADES NORMANDES | G41: NORMAND DIRECT TERROIR | H41: Boîte fer | I41: 150 g | J41: NON | K41: 5.5 % | L41: 7.31 | M41: 17.5 | N41: PROPOSÉ | O41: =IF(M41="","",M41-L41) | P41: =IF(OR(M41="",M41=0),"",(M41-L41)/M41) | Q41: =IF(OR(M41="",L41=0,L41=""),"",M41/L41) | R41: =IF(M41="","",M41*1.055)
A42: PROD-0287 | B42: BISCUITS 150g Caen cœur de ville Aquarelle | C42: BISCUITERIE | D42: BISCUIT | E42: SIGNATURE | F42: BALADES NORMANDES | G42: NORMAND DIRECT TERROIR | H42: Boîte fer | I42: 150 g | J42: NON | K42: 5.5 % | L42: 7.31 | M42: 17.5 | N42: PROPOSÉ | O42: =IF(M42="","",M42-L42) | P42: =IF(OR(M42="",M42=0),"",(M42-L42)/M42) | Q42: =IF(OR(M42="",L42=0,L42=""),"",M42/L42) | R42: =IF(M42="","",M42*1.055)
A43: PROD-0288 | B43: Biscuits 150g Pays D'Auge Aquarelle | C43: BISCUITERIE | D43: BISCUIT | E43: SIGNATURE | F43: BALADES NORMANDES | G43: NORMAND DIRECT TERROIR | H43: Boîte fer | I43: 150 g | J43: NON | K43: 5.5 % | L43: 7.31 | M43: 17.5 | N43: PROPOSÉ | O43: =IF(M43="","",M43-L43) | P43: =IF(OR(M43="",M43=0),"",(M43-L43)/M43) | Q43: =IF(OR(M43="",L43=0,L43=""),"",M43/L43) | R43: =IF(M43="","",M43*1.055)
A44: PROD-0289 | B44: Biscuits 150g Cambremer Aquarelle | C44: BISCUITERIE | D44: BISCUIT | E44: SIGNATURE | F44: BALADES NORMANDES | G44: NORMAND DIRECT TERROIR | H44: Boîte fer | I44: 150 g | J44: NON | K44: 5.5 % | L44: 7.31 | M44: 17.5 | N44: PROPOSÉ | O44: =IF(M44="","",M44-L44) | P44: =IF(OR(M44="",M44=0),"",(M44-L44)/M44) | Q44: =IF(OR(M44="",L44=0,L44=""),"",M44/L44) | R44: =IF(M44="","",M44*1.055)
A45: PROD-0294 | B45: Biscuits 120g JEEP | C45: BISCUITERIE | D45: BISCUIT | E45: SIGNATURE | F45: BALADES NORMANDES | G45: NORMAND DIRECT TERROIR | H45: D-DAY Boîte métal | I45: 120 g | J45: NON | K45: 20 % | L45: 7.31 | M45: 17.5 | N45: PROPOSÉ | O45: =IF(M45="","",M45-L45) | P45: =IF(OR(M45="",M45=0),"",(M45-L45)/M45) | Q45: =IF(OR(M45="",L45=0,L45=""),"",M45/L45) | R45: =IF(M45="","",M45*1.2)
A46: PROD-0295 | B46: Biscuits 120g Barge | C46: BISCUITERIE | D46: BISCUIT | E46: SIGNATURE | F46: BALADES NORMANDES | G46: NORMAND DIRECT TERROIR | H46: D-DAY Boîte métal | I46: 120 g | J46: NON | K46: 20 % | L46: 7.31 | M46: 17.5 | N46: PROPOSÉ | O46: =IF(M46="","",M46-L46) | P46: =IF(OR(M46="",M46=0),"",(M46-L46)/M46) | Q46: =IF(OR(M46="",L46=0,L46=""),"",M46/L46) | R46: =IF(M46="","",M46*1.2)
A47: PROD-0031 | B47: Batonnet feuilleté noir 200 grs | C47: BISCUITERIE | D47: BISCUIT | E47: SIGNATURE | F47: BISCUITERIE DE QUINEVILLE | G47: NORMAND DIRECT TERROIR | I47: 200 g | J47: NON | K47: 5.5 % | L47: 6.95 | M47: 16.7 | N47: PROPOSÉ | O47: =IF(M47="","",M47-L47) | P47: =IF(OR(M47="",M47=0),"",(M47-L47)/M47) | Q47: =IF(OR(M47="",L47=0,L47=""),"",M47/L47) | R47: =IF(M47="","",M47*1.055)
A48: PROD-0027 | B48: Tuiles chocolat noir 150gr | C48: BISCUITERIE | D48: BISCUIT | E48: SIGNATURE | F48: BISCUITERIE DE QUINEVILLE | G48: NORMAND DIRECT TERROIR | I48: 150 g | J48: NON | K48: 5.5 % | L48: 6.6 | M48: 15.8 | N48: PROPOSÉ | O48: =IF(M48="","",M48-L48) | P48: =IF(OR(M48="",M48=0),"",(M48-L48)/M48) | Q48: =IF(OR(M48="",L48=0,L48=""),"",M48/L48) | R48: =IF(M48="","",M48*1.055)
A49: PROD-0028 | B49: Tuiles chocolat lacté 150gr | C49: BISCUITERIE | D49: BISCUIT | E49: SIGNATURE | F49: BISCUITERIE DE QUINEVILLE | G49: NORMAND DIRECT TERROIR | I49: 150 g | J49: NON | K49: 20 % | L49: 6.6 | M49: 15.8 | N49: PROPOSÉ | O49: =IF(M49="","",M49-L49) | P49: =IF(OR(M49="",M49=0),"",(M49-L49)/M49) | Q49: =IF(OR(M49="",L49=0,L49=""),"",M49/L49) | R49: =IF(M49="","",M49*1.2)
A50: PROD-0004 | B50: Biscuits assortiment 250 grs | C50: BISCUITERIE | D50: BISCUIT | E50: SIGNATURE | F50: BISCUITERIE DE QUINEVILLE | G50: NORMAND DIRECT TERROIR | I50: 250 g | J50: NON | K50: 5.5 % | L50: 5.9 | M50: 14.2 | N50: PROPOSÉ | O50: =IF(M50="","",M50-L50) | P50: =IF(OR(M50="",M50=0),"",(M50-L50)/M50) | Q50: =IF(OR(M50="",L50=0,L50=""),"",M50/L50) | R50: =IF(M50="","",M50*1.055)
A51: PROD-0662 | B51: Cidre Tonique | C51: BOISSON_ALCOOLISEE | D51: CIDRE | E51: ESSENTIEL | F51: SARL DOMAINE DE BILLY | G51: SARL DOMAINE DE BILLY | H51: 75cl | I51: 750 ml | J51: OUI | K51: À CONFIRMER | L51: 4.5 | M51: 8.8 | N51: PROPOSÉ | O51: =IF(M51="","",M51-L51) | P51: =IF(OR(M51="",M51=0),"",(M51-L51)/M51) | Q51: =IF(OR(M51="",L51=0,L51=""),"",M51/L51) | R51: =IF(M51="","","TVA à confirmer")
A52: PROD-0670 | B52: Poiré | C52: BOISSON_ALCOOLISEE | D52: POIRE | E52: ESSENTIEL | F52: SARL DOMAINE DE BILLY | G52: SARL DOMAINE DE BILLY | H52: 75 cl | I52: 750 ml | J52: OUI | K52: À CONFIRMER | L52: 4.45 | M52: 8.7 | N52: PROPOSÉ | O52: =IF(M52="","",M52-L52) | P52: =IF(OR(M52="",M52=0),"",(M52-L52)/M52) | Q52: =IF(OR(M52="",L52=0,L52=""),"",M52/L52) | R52: =IF(M52="","","TVA à confirmer")
A53: PROD-0663 | B53: Cidre Sauvage | C53: BOISSON_ALCOOLISEE | D53: CIDRE | E53: ESSENTIEL | F53: SARL DOMAINE DE BILLY | G53: SARL DOMAINE DE BILLY | H53: 75cl | I53: 750 ml | J53: OUI | K53: À CONFIRMER | L53: 4.4 | M53: 8.6 | N53: PROPOSÉ | O53: =IF(M53="","",M53-L53) | P53: =IF(OR(M53="",M53=0),"",(M53-L53)/M53) | Q53: =IF(OR(M53="",L53=0,L53=""),"",M53/L53) | R53: =IF(M53="","","TVA à confirmer")
A54: PROD-0354 | B54: Cidre Cotentin demi-sec 75 cl | C54: BOISSON_ALCOOLISEE | D54: CIDRE | E54: ESSENTIEL | F54: GAEC DE CLAIDS | G54: NORMAND DIRECT TERROIR | I54: 750 ml | J54: OUI | K54: 20 % | L54: 4.32 | M54: 8.4 | N54: PROPOSÉ | O54: =IF(M54="","",M54-L54) | P54: =IF(OR(M54="",M54=0),"",(M54-L54)/M54) | Q54: =IF(OR(M54="",L54=0,L54=""),"",M54/L54) | R54: =IF(M54="","",M54*1.2)
A55: PROD-0316 | B55: Cidre bio cuvée gourmande demi sec 75 cl | C55: BOISSON_ALCOOLISEE | D55: CIDRE | E55: ESSENTIEL | F55: MAISON HEROUT | G55: NORMAND DIRECT TERROIR | I55: 750 ml | J55: OUI | K55: 20 % | L55: 4.29 | M55: 8.4 | N55: PROPOSÉ | O55: =IF(M55="","",M55-L55) | P55: =IF(OR(M55="",M55=0),"",(M55-L55)/M55) | Q55: =IF(OR(M55="",L55=0,L55=""),"",M55/L55) | R55: =IF(M55="","",M55*1.2)
A56: PROD-0324 | B56: Amour d'Hérout brut 75 cl cidre IGP | C56: BOISSON_ALCOOLISEE | D56: CIDRE | E56: ESSENTIEL | F56: MAISON HEROUT | G56: NORMAND DIRECT TERROIR | I56: 750 ml | J56: OUI | K56: 20 % | L56: 3.85 | M56: 7.5 | N56: PROPOSÉ | O56: =IF(M56="","",M56-L56) | P56: =IF(OR(M56="",M56=0),"",(M56-L56)/M56) | Q56: =IF(OR(M56="",L56=0,L56=""),"",M56/L56) | R56: =IF(M56="","",M56*1.2)
A57: PROD-0350 | B57: Cidre Cotentin extra brut 75 cl | C57: BOISSON_ALCOOLISEE | D57: CIDRE | E57: ESSENTIEL | F57: GAEC DE CLAIDS | G57: NORMAND DIRECT TERROIR | I57: 750 ml | J57: OUI | K57: 20 % | L57: 3.8 | M57: 7.4 | N57: PROPOSÉ | O57: =IF(M57="","",M57-L57) | P57: =IF(OR(M57="",M57=0),"",(M57-L57)/M57) | Q57: =IF(OR(M57="",L57=0,L57=""),"",M57/L57) | R57: =IF(M57="","",M57*1.2)
A58: PROD-0352 | B58: Cidre Cotentin brut 75 cl | C58: BOISSON_ALCOOLISEE | D58: CIDRE | E58: ESSENTIEL | F58: GAEC DE CLAIDS | G58: NORMAND DIRECT TERROIR | I58: 750 ml | J58: OUI | K58: 20 % | L58: 3.8 | M58: 7.4 | N58: PROPOSÉ | O58: =IF(M58="","",M58-L58) | P58: =IF(OR(M58="",M58=0),"",(M58-L58)/M58) | Q58: =IF(OR(M58="",L58=0,L58=""),"",M58/L58) | R58: =IF(M58="","",M58*1.2)
A59: PROD-0382 | B59: Bière triple 75 cl / 9 Triple à la mode de Caen | C59: BOISSON_ALCOOLISEE | D59: BIERE | E59: ESSENTIEL | F59: BRASSERIE LA LIE | G59: NORMAND DIRECT TERROIR | I59: 750 ml | J59: OUI | K59: 20 % | L59: 3.8 | M59: 7.4 | N59: PROPOSÉ | O59: =IF(M59="","",M59-L59) | P59: =IF(OR(M59="",M59=0),"",(M59-L59)/M59) | Q59: =IF(OR(M59="",L59=0,L59=""),"",M59/L59) | R59: =IF(M59="","",M59*1.2)
A60: PROD-0661 | B60: Cidre Fraîcheur | C60: BOISSON_ALCOOLISEE | D60: CIDRE | E60: ESSENTIEL | F60: SARL DOMAINE DE BILLY | G60: SARL DOMAINE DE BILLY | H60: 75cl | I60: 750 ml | J60: OUI | K60: À CONFIRMER | L60: 3.65 | M60: 7.1 | N60: PROPOSÉ | O60: =IF(M60="","",M60-L60) | P60: =IF(OR(M60="",M60=0),"",(M60-L60)/M60) | Q60: =IF(OR(M60="",L60=0,L60=""),"",M60/L60) | R60: =IF(M60="","","TVA à confirmer")
A61: PROD-0374 | B61: Bière blonde 75 cl / 9 Au prés de ma blonde | C61: BOISSON_ALCOOLISEE | D61: BIERE | E61: ESSENTIEL | F61: BRASSERIE LA LIE | G61: NORMAND DIRECT TERROIR | I61: 750 ml | J61: OUI | K61: 20 % | L61: 3.64 | M61: 7.1 | N61: PROPOSÉ | O61: =IF(M61="","",M61-L61) | P61: =IF(OR(M61="",M61=0),"",(M61-L61)/M61) | Q61: =IF(OR(M61="",L61=0,L61=""),"",M61/L61) | R61: =IF(M61="","",M61*1.2)
A62: PROD-0376 | B62: Bière ambrée 75 cl / 9 Ambrée du hameau | C62: BOISSON_ALCOOLISEE | D62: BIERE | E62: ESSENTIEL | F62: BRASSERIE LA LIE | G62: NORMAND DIRECT TERROIR | I62: 750 ml | J62: OUI | K62: 20 % | L62: 3.64 | M62: 7.1 | N62: PROPOSÉ | O62: =IF(M62="","",M62-L62) | P62: =IF(OR(M62="",M62=0),"",(M62-L62)/M62) | Q62: =IF(OR(M62="",L62=0,L62=""),"",M62/L62) | R62: =IF(M62="","",M62*1.2)
A63: PROD-0378 | B63: Bière blanche 75 cl / 9 La Caennette | C63: BOISSON_ALCOOLISEE | D63: BIERE | E63: ESSENTIEL | F63: BRASSERIE LA LIE | G63: NORMAND DIRECT TERROIR | I63: 750 ml | J63: OUI | K63: 20 % | L63: 3.64 | M63: 7.1 | N63: PROPOSÉ | O63: =IF(M63="","",M63-L63) | P63: =IF(OR(M63="",M63=0),"",(M63-L63)/M63) | Q63: =IF(OR(M63="",L63=0,L63=""),"",M63/L63) | R63: =IF(M63="","",M63*1.2)
A64: PROD-0380 | B64: Bière brune 75 cl / 9 Quai des brunes | C64: BOISSON_ALCOOLISEE | D64: BIERE | E64: ESSENTIEL | F64: BRASSERIE LA LIE | G64: NORMAND DIRECT TERROIR | I64: 750 ml | J64: OUI | K64: 20 % | L64: 3.64 | M64: 7.1 | N64: PROPOSÉ | O64: =IF(M64="","",M64-L64) | P64: =IF(OR(M64="",M64=0),"",(M64-L64)/M64) | Q64: =IF(OR(M64="",L64=0,L64=""),"",M64/L64) | R64: =IF(M64="","",M64*1.2)
A65: PROD-0384 | B65: Bière rousse Conté fleurette 75 cl / 9 | C65: BOISSON_ALCOOLISEE | D65: BIERE | E65: ESSENTIEL | F65: BRASSERIE LA LIE | G65: NORMAND DIRECT TERROIR | I65: 750 ml | J65: OUI | K65: 20 % | L65: 3.64 | M65: 7.1 | N65: PROPOSÉ | O65: =IF(M65="","",M65-L65) | P65: =IF(OR(M65="",M65=0),"",(M65-L65)/M65) | Q65: =IF(OR(M65="",L65=0,L65=""),"",M65/L65) | R65: =IF(M65="","",M65*1.2)
A66: PROD-0386 | B66: Bière blonde Pale Ale 75 cl / 9 la Suisse Normande | C66: BOISSON_ALCOOLISEE | D66: BIERE | E66: ESSENTIEL | F66: BRASSERIE LA LIE | G66: NORMAND DIRECT TERROIR | I66: 750 ml | J66: OUI | K66: 20 % | L66: 3.64 | M66: 7.1 | N66: PROPOSÉ | O66: =IF(M66="","",M66-L66) | P66: =IF(OR(M66="",M66=0),"",(M66-L66)/M66) | Q66: =IF(OR(M66="",L66=0,L66=""),"",M66/L66) | R66: =IF(M66="","",M66*1.2)
A67: PROD-0388 | B67: Bière de Noel 75 cl / 9 ça sent le sapin | C67: BOISSON_ALCOOLISEE | D67: BIERE | E67: ESSENTIEL | F67: BRASSERIE LA LIE | G67: NORMAND DIRECT TERROIR | I67: 750 ml | J67: OUI | K67: 20 % | L67: 3.64 | M67: 7.1 | N67: PROPOSÉ | O67: =IF(M67="","",M67-L67) | P67: =IF(OR(M67="",M67=0),"",(M67-L67)/M67) | Q67: =IF(OR(M67="",L67=0,L67=""),"",M67/L67) | R67: =IF(M67="","",M67*1.2)
A68: PROD-0390 | B68: Bière édition limité du moment 75 cl / 9 | C68: BOISSON_ALCOOLISEE | D68: BIERE | E68: ESSENTIEL | F68: BRASSERIE LA LIE | G68: NORMAND DIRECT TERROIR | I68: 750 ml | J68: OUI | K68: 20 % | L68: 3.64 | M68: 7.1 | N68: PROPOSÉ | O68: =IF(M68="","",M68-L68) | P68: =IF(OR(M68="",M68=0),"",(M68-L68)/M68) | Q68: =IF(OR(M68="",L68=0,L68=""),"",M68/L68) | R68: =IF(M68="","",M68*1.2)
A69: PROD-0355 | B69: Cidre Cotentin doux 75 cl | C69: BOISSON_ALCOOLISEE | D69: CIDRE | E69: ESSENTIEL | F69: GAEC DE CLAIDS | G69: NORMAND DIRECT TERROIR | I69: 750 ml | J69: OUI | K69: 20 % | L69: 3.6 | M69: 7 | N69: PROPOSÉ | O69: =IF(M69="","",M69-L69) | P69: =IF(OR(M69="",M69=0),"",(M69-L69)/M69) | Q69: =IF(OR(M69="",L69=0,L69=""),"",M69/L69) | R69: =IF(M69="","",M69*1.2)
A70: PROD-0659 | B70: Cidre Corsé | C70: BOISSON_ALCOOLISEE | D70: CIDRE | E70: ESSENTIEL | F70: SARL DOMAINE DE BILLY | G70: SARL DOMAINE DE BILLY | H70: 75cl | I70: 750 ml | J70: OUI | K70: À CONFIRMER | L70: 3.36 | M70: 6.6 | N70: PROPOSÉ | O70: =IF(M70="","",M70-L70) | P70: =IF(OR(M70="",M70=0),"",(M70-L70)/M70) | Q70: =IF(OR(M70="",L70=0,L70=""),"",M70/L70) | R70: =IF(M70="","","TVA à confirmer")
A71: PROD-0660 | B71: Cidre Fruité | C71: BOISSON_ALCOOLISEE | D71: CIDRE | E71: ESSENTIEL | F71: SARL DOMAINE DE BILLY | G71: SARL DOMAINE DE BILLY | H71: 75cl | I71: 750 ml | J71: OUI | K71: À CONFIRMER | L71: 3.36 | M71: 6.6 | N71: PROPOSÉ | O71: =IF(M71="","",M71-L71) | P71: =IF(OR(M71="",M71=0),"",(M71-L71)/M71) | Q71: =IF(OR(M71="",L71=0,L71=""),"",M71/L71) | R71: =IF(M71="","","TVA à confirmer")
A72: PROD-0353 | B72: Cidre Cotentin brut 33 cl | C72: BOISSON_ALCOOLISEE | D72: CIDRE | E72: ESSENTIEL | F72: GAEC DE CLAIDS | G72: NORMAND DIRECT TERROIR | I72: 330 ml | J72: OUI | K72: 20 % | L72: 2.25 | M72: 4.8 | N72: PROPOSÉ | O72: =IF(M72="","",M72-L72) | P72: =IF(OR(M72="",M72=0),"",(M72-L72)/M72) | Q72: =IF(OR(M72="",L72=0,L72=""),"",M72/L72) | R72: =IF(M72="","",M72*1.2)
A73: PROD-0381 | B73: Bière triple 33 cl / 24 Triple à la mode de Caen | C73: BOISSON_ALCOOLISEE | D73: BIERE | E73: ESSENTIEL | F73: BRASSERIE LA LIE | G73: NORMAND DIRECT TERROIR | I73: 330 ml | J73: OUI | K73: 20 % | L73: 2.01 | M73: 4.3 | N73: PROPOSÉ | O73: =IF(M73="","",M73-L73) | P73: =IF(OR(M73="",M73=0),"",(M73-L73)/M73) | Q73: =IF(OR(M73="",L73=0,L73=""),"",M73/L73) | R73: =IF(M73="","",M73*1.2)
A74: PROD-0373 | B74: Bière blonde 33 cl / 24 Au prés de ma blonde | C74: BOISSON_ALCOOLISEE | D74: BIERE | E74: ESSENTIEL | F74: BRASSERIE LA LIE | G74: NORMAND DIRECT TERROIR | I74: 330 ml | J74: OUI | K74: 20 % | L74: 1.96 | M74: 4.2 | N74: PROPOSÉ | O74: =IF(M74="","",M74-L74) | P74: =IF(OR(M74="",M74=0),"",(M74-L74)/M74) | Q74: =IF(OR(M74="",L74=0,L74=""),"",M74/L74) | R74: =IF(M74="","",M74*1.2)
A75: PROD-0375 | B75: Bière ambrée 33 cl / 24 Ambrée du hameau | C75: BOISSON_ALCOOLISEE | D75: BIERE | E75: ESSENTIEL | F75: BRASSERIE LA LIE | G75: NORMAND DIRECT TERROIR | I75: 330 ml | J75: OUI | K75: 20 % | L75: 1.96 | M75: 4.2 | N75: PROPOSÉ | O75: =IF(M75="","",M75-L75) | P75: =IF(OR(M75="",M75=0),"",(M75-L75)/M75) | Q75: =IF(OR(M75="",L75=0,L75=""),"",M75/L75) | R75: =IF(M75="","",M75*1.2)
A76: PROD-0377 | B76: Bière blanche 33 cl / 24 La Caennette | C76: BOISSON_ALCOOLISEE | D76: BIERE | E76: ESSENTIEL | F76: BRASSERIE LA LIE | G76: NORMAND DIRECT TERROIR | I76: 330 ml | J76: OUI | K76: 20 % | L76: 1.96 | M76: 4.2 | N76: PROPOSÉ | O76: =IF(M76="","",M76-L76) | P76: =IF(OR(M76="",M76=0),"",(M76-L76)/M76) | Q76: =IF(OR(M76="",L76=0,L76=""),"",M76/L76) | R76: =IF(M76="","",M76*1.2)
A77: PROD-0379 | B77: Bière brune 33 cl / 24 Quai des brune | C77: BOISSON_ALCOOLISEE | D77: BIERE | E77: ESSENTIEL | F77: BRASSERIE LA LIE | G77: NORMAND DIRECT TERROIR | I77: 330 ml | J77: OUI | K77: 20 % | L77: 1.96 | M77: 4.2 | N77: PROPOSÉ | O77: =IF(M77="","",M77-L77) | P77: =IF(OR(M77="",M77=0),"",(M77-L77)/M77) | Q77: =IF(OR(M77="",L77=0,L77=""),"",M77/L77) | R77: =IF(M77="","",M77*1.2)
A78: PROD-0383 | B78: Bière rousse Conté fleurette 33 cl / 24 | C78: BOISSON_ALCOOLISEE | D78: BIERE | E78: ESSENTIEL | F78: BRASSERIE LA LIE | G78: NORMAND DIRECT TERROIR | I78: 330 ml | J78: OUI | K78: 20 % | L78: 1.96 | M78: 4.2 | N78: PROPOSÉ | O78: =IF(M78="","",M78-L78) | P78: =IF(OR(M78="",M78=0),"",(M78-L78)/M78) | Q78: =IF(OR(M78="",L78=0,L78=""),"",M78/L78) | R78: =IF(M78="","",M78*1.2)
A79: PROD-0385 | B79: Bière blonde Pale Ale 33 cl / 24 la Suisse Normande | C79: BOISSON_ALCOOLISEE | D79: BIERE | E79: ESSENTIEL | F79: BRASSERIE LA LIE | G79: NORMAND DIRECT TERROIR | I79: 330 ml | J79: OUI | K79: 20 % | L79: 1.96 | M79: 4.2 | N79: PROPOSÉ | O79: =IF(M79="","",M79-L79) | P79: =IF(OR(M79="",M79=0),"",(M79-L79)/M79) | Q79: =IF(OR(M79="",L79=0,L79=""),"",M79/L79) | R79: =IF(M79="","",M79*1.2)
A80: PROD-0387 | B80: Bière de Noel 33 cl / 24 ça sent le sapin | C80: BOISSON_ALCOOLISEE | D80: BIERE | E80: ESSENTIEL | F80: BRASSERIE LA LIE | G80: NORMAND DIRECT TERROIR | I80: 330 ml | J80: OUI | K80: 20 % | L80: 1.96 | M80: 4.2 | N80: PROPOSÉ | O80: =IF(M80="","",M80-L80) | P80: =IF(OR(M80="",M80=0),"",(M80-L80)/M80) | Q80: =IF(OR(M80="",L80=0,L80=""),"",M80/L80) | R80: =IF(M80="","",M80*1.2)
A81: PROD-0389 | B81: Bière édition limité du moment 33 cl / 24 | C81: BOISSON_ALCOOLISEE | D81: BIERE | E81: ESSENTIEL | F81: BRASSERIE LA LIE | G81: NORMAND DIRECT TERROIR | I81: 330 ml | J81: OUI | K81: 20 % | L81: 1.96 | M81: 4.2 | N81: PROPOSÉ | O81: =IF(M81="","",M81-L81) | P81: =IF(OR(M81="",M81=0),"",(M81-L81)/M81) | Q81: =IF(OR(M81="",L81=0,L81=""),"",M81/L81) | R81: =IF(M81="","",M81*1.2)
A82: PROD-0323 | B82: Amour d'Hérout brut 33 cl cidre IGP | C82: BOISSON_ALCOOLISEE | D82: CIDRE | E82: ESSENTIEL | F82: MAISON HEROUT | G82: NORMAND DIRECT TERROIR | I82: 330 ml | J82: OUI | K82: 20 % | L82: 1.93 | M82: 4.1 | N82: PROPOSÉ | O82: =IF(M82="","",M82-L82) | P82: =IF(OR(M82="",M82=0),"",(M82-L82)/M82) | Q82: =IF(OR(M82="",L82=0,L82=""),"",M82/L82) | R82: =IF(M82="","",M82*1.2)
A83: PROD-0325 | B83: Amour d'Hérout doux 33 cl cidre IGP | C83: BOISSON_ALCOOLISEE | D83: CIDRE | E83: ESSENTIEL | F83: MAISON HEROUT | G83: NORMAND DIRECT TERROIR | I83: 330 ml | J83: OUI | K83: 20 % | L83: 1.93 | M83: 4.1 | N83: PROPOSÉ | O83: =IF(M83="","",M83-L83) | P83: =IF(OR(M83="",M83=0),"",(M83-L83)/M83) | Q83: =IF(OR(M83="",L83=0,L83=""),"",M83/L83) | R83: =IF(M83="","",M83*1.2)
A84: PROD-0665 | B84: Cidre Fruité | C84: BOISSON_ALCOOLISEE | D84: CIDRE | E84: ESSENTIEL | F84: SARL DOMAINE DE BILLY | G84: SARL DOMAINE DE BILLY | H84: 33cl | I84: 330 ml | J84: OUI | K84: À CONFIRMER | L84: 1.75 | M84: 3.8 | N84: PROPOSÉ | O84: =IF(M84="","",M84-L84) | P84: =IF(OR(M84="",M84=0),"",(M84-L84)/M84) | Q84: =IF(OR(M84="",L84=0,L84=""),"",M84/L84) | R84: =IF(M84="","","TVA à confirmer")
A85: PROD-0666 | B85: Cidre Fraîcheur | C85: BOISSON_ALCOOLISEE | D85: CIDRE | E85: ESSENTIEL | F85: SARL DOMAINE DE BILLY | G85: SARL DOMAINE DE BILLY | H85: 33cl | I85: 330 ml | J85: OUI | K85: À CONFIRMER | L85: 1.75 | M85: 3.8 | N85: PROPOSÉ | O85: =IF(M85="","",M85-L85) | P85: =IF(OR(M85="",M85=0),"",(M85-L85)/M85) | Q85: =IF(OR(M85="",L85=0,L85=""),"",M85/L85) | R85: =IF(M85="","","TVA à confirmer")
A86: PROD-0667 | B86: Cidre Tonique | C86: BOISSON_ALCOOLISEE | D86: CIDRE | E86: ESSENTIEL | F86: SARL DOMAINE DE BILLY | G86: SARL DOMAINE DE BILLY | H86: 33cl | I86: 330 ml | J86: OUI | K86: À CONFIRMER | L86: 1.75 | M86: 3.8 | N86: PROPOSÉ | O86: =IF(M86="","",M86-L86) | P86: =IF(OR(M86="",M86=0),"",(M86-L86)/M86) | Q86: =IF(OR(M86="",L86=0,L86=""),"",M86/L86) | R86: =IF(M86="","","TVA à confirmer")
A87: PROD-0664 | B87: Terroir Chic | C87: BOISSON_ALCOOLISEE | D87: CIDRE | E87: ESSENTIEL | F87: SARL DOMAINE DE BILLY | G87: SARL DOMAINE DE BILLY | H87: 33cl | I87: 330 ml | J87: OUI | K87: À CONFIRMER | L87: 1.71 | M87: 3.7 | N87: PROPOSÉ | O87: =IF(M87="","",M87-L87) | P87: =IF(OR(M87="",M87=0),"",(M87-L87)/M87) | Q87: =IF(OR(M87="",L87=0,L87=""),"",M87/L87) | R87: =IF(M87="","","TVA à confirmer")
A88: PROD-0701 | B88: Le Rosé Marin 75cl btlle | C88: BOISSON_ALCOOLISEE | D88: VIN | E88: SIGNATURE | F88: DOMAINE DE BRUCAN | G88: DOMAINE DE BRUCAN | H88: bouteille 75 cl (mention « btlle » sur la facture) | I88: 750 ml | J88: OUI | K88: 20 % | L88: 9.5 | M88: 15.3 | N88: PROPOSÉ | O88: =IF(M88="","",M88-L88) | P88: =IF(OR(M88="",M88=0),"",(M88-L88)/M88) | Q88: =IF(OR(M88="",L88=0,L88=""),"",M88/L88) | R88: =IF(M88="","",M88*1.2)
A89: PROD-0405 | B89: Gin 40 ° 20 cl | C89: BOISSON_ALCOOLISEE | D89: SPIRITUEUX | E89: SIGNATURE | F89: DISTILLERIE C'EST NOUS | G89: NORMAND DIRECT TERROIR | I89: 200 ml | J89: OUI | K89: 20 % | L89: 9.4 | M89: 15.1 | N89: PROPOSÉ | O89: =IF(M89="","",M89-L89) | P89: =IF(OR(M89="",M89=0),"",(M89-L89)/M89) | Q89: =IF(OR(M89="",L89=0,L89=""),"",M89/L89) | R89: =IF(M89="","",M89*1.2)
A90: PROD-0410 | B90: Vodka Normande 40° 20 cl | C90: BOISSON_ALCOOLISEE | D90: SPIRITUEUX | E90: SIGNATURE | F90: DISTILLERIE C'EST NOUS | G90: NORMAND DIRECT TERROIR | I90: 200 ml | J90: OUI | K90: 20 % | L90: 9.4 | M90: 15.1 | N90: PROPOSÉ | O90: =IF(M90="","",M90-L90) | P90: =IF(OR(M90="",M90=0),"",(M90-L90)/M90) | Q90: =IF(OR(M90="",L90=0,L90=""),"",M90/L90) | R90: =IF(M90="","",M90*1.2)
A91: PROD-0399 | B91: PINOT NOIR 50 CL rouge 12 ° en coffret de 6 | C91: BOISSON_ALCOOLISEE | D91: VIN | E91: SIGNATURE | F91: LES ARPENTS DU SOLEIL | G91: NORMAND DIRECT TERROIR | I91: 500 ml | J91: OUI | K91: 20 % | L91: 8.8 | M91: 14.2 | N91: PROPOSÉ | O91: =IF(M91="","",M91-L91) | P91: =IF(OR(M91="",M91=0),"",(M91-L91)/M91) | Q91: =IF(OR(M91="",L91=0,L91=""),"",M91/L91) | R91: =IF(M91="","",M91*1.2)
A92: PROD-0402 | B92: PINOT Gris 50 CL en coffret de 6 | C92: BOISSON_ALCOOLISEE | D92: VIN | E92: SIGNATURE | F92: LES ARPENTS DU SOLEIL | G92: NORMAND DIRECT TERROIR | I92: 500 ml | J92: OUI | K92: 20 % | L92: 8.8 | M92: 14.2 | N92: PROPOSÉ | O92: =IF(M92="","",M92-L92) | P92: =IF(OR(M92="",M92=0),"",(M92-L92)/M92) | Q92: =IF(OR(M92="",L92=0,L92=""),"",M92/L92) | R92: =IF(M92="","",M92*1.2)
A93: PROD-0412 | B93: Liqueur de café Cold brew 25° 20 cl | C93: BOISSON_ALCOOLISEE | D93: LIQUEUR | E93: SIGNATURE | F93: DISTILLERIE C'EST NOUS | G93: NORMAND DIRECT TERROIR | I93: 200 ml | J93: OUI | K93: 20 % | L93: 8.5 | M93: 14.1 | N93: PROPOSÉ | O93: =IF(M93="","",M93-L93) | P93: =IF(OR(M93="",M93=0),"",(M93-L93)/M93) | Q93: =IF(OR(M93="",L93=0,L93=""),"",M93/L93) | R93: =IF(M93="","",M93*1.2)
A94: PROD-0319 | B94: Cidre bio micro cuvée N°2 cidre dégorgé 75 cl 2020 | C94: BOISSON_ALCOOLISEE | D94: CIDRE | E94: SIGNATURE | F94: MAISON HEROUT | G94: NORMAND DIRECT TERROIR | I94: 750 ml | J94: OUI | K94: 20 % | L94: 8.36 | M94: 15 | N94: PROPOSÉ | O94: =IF(M94="","",M94-L94) | P94: =IF(OR(M94="",M94=0),"",(M94-L94)/M94) | Q94: =IF(OR(M94="",L94=0,L94=""),"",M94/L94) | R94: =IF(M94="","",M94*1.2)
A95: PROD-0688 | B95: Cidre de glace | C95: BOISSON_ALCOOLISEE | D95: CIDRE_DE_GLACE | E95: SIGNATURE | F95: SARL DOMAINE DE BILLY | G95: SARL DOMAINE DE BILLY | H95: 20 cl | I95: 200 ml | J95: OUI | K95: À CONFIRMER | L95: 8 | M95: 13.6 | N95: PROPOSÉ | O95: =IF(M95="","",M95-L95) | P95: =IF(OR(M95="",M95=0),"",(M95-L95)/M95) | Q95: =IF(OR(M95="",L95=0,L95=""),"",M95/L95) | R95: =IF(M95="","","TVA à confirmer")
A96: PROD-0351 | B96: Cidre Cotentin extra brut selection 75 cl | C96: BOISSON_ALCOOLISEE | D96: CIDRE | E96: SIGNATURE | F96: GAEC DE CLAIDS | G96: NORMAND DIRECT TERROIR | I96: 750 ml | J96: OUI | K96: 20 % | L96: 7.6 | M96: 14.8 | N96: PROPOSÉ | O96: =IF(M96="","",M96-L96) | P96: =IF(OR(M96="",M96=0),"",(M96-L96)/M96) | Q96: =IF(OR(M96="",L96=0,L96=""),"",M96/L96) | R96: =IF(M96="","",M96*1.2)
A97: PROD-0317 | B97: Cidre bio micro cuvée N°1 vieilli fût chêne75 cl 2021 | C97: BOISSON_ALCOOLISEE | D97: CIDRE | E97: SIGNATURE | F97: MAISON HEROUT | G97: NORMAND DIRECT TERROIR | I97: 750 ml | J97: OUI | K97: 20 % | L97: 7.48 | M97: 14.6 | N97: PROPOSÉ | O97: =IF(M97="","",M97-L97) | P97: =IF(OR(M97="",M97=0),"",(M97-L97)/M97) | Q97: =IF(OR(M97="",L97=0,L97=""),"",M97/L97) | R97: =IF(M97="","",M97*1.2)
A98: PROD-0321 | B98: Cidre bio micro cuvée N°4 Variétés acidulées | C98: BOISSON_ALCOOLISEE | D98: CIDRE | E98: SIGNATURE | F98: MAISON HEROUT | G98: NORMAND DIRECT TERROIR | J98: OUI | K98: 20 % | L98: 7.15 | M98: 13.9 | N98: PROPOSÉ | O98: =IF(M98="","",M98-L98) | P98: =IF(OR(M98="",M98=0),"",(M98-L98)/M98) | Q98: =IF(OR(M98="",L98=0,L98=""),"",M98/L98) | R98: =IF(M98="","",M98*1.2)
A99: PROD-0322 | B99: Cidre bio micro cuvée N°5 assemblage 50% amer 50% acidulé | C99: BOISSON_ALCOOLISEE | D99: CIDRE | E99: SIGNATURE | F99: MAISON HEROUT | G99: NORMAND DIRECT TERROIR | J99: OUI | K99: 20 % | L99: 7.15 | M99: 13.9 | N99: PROPOSÉ | O99: =IF(M99="","",M99-L99) | P99: =IF(OR(M99="",M99=0),"",(M99-L99)/M99) | Q99: =IF(OR(M99="",L99=0,L99=""),"",M99/L99) | R99: =IF(M99="","",M99*1.2)
A100: PROD-0401 | B100: AUXERROIS 50 CL blanc 12 ° en coffret de 6 | C100: BOISSON_ALCOOLISEE | D100: VIN | E100: SIGNATURE | F100: LES ARPENTS DU SOLEIL | G100: NORMAND DIRECT TERROIR | I100: 500 ml | J100: OUI | K100: 20 % | L100: 6.75 | M100: 11.8 | N100: PROPOSÉ | O100: =IF(M100="","",M100-L100) | P100: =IF(OR(M100="",M100=0),"",(M100-L100)/M100) | Q100: =IF(OR(M100="",L100=0,L100=""),"",M100/L100) | R100: =IF(M100="","",M100*1.2)
A101: PROD-0312 | B101: Cidre bio Cotentin AOC brut 75 cl | C101: BOISSON_ALCOOLISEE | D101: CIDRE | E101: SIGNATURE | F101: MAISON HEROUT | G101: NORMAND DIRECT TERROIR | I101: 750 ml | J101: OUI | K101: 20 % | L101: 4.62 | M101: 9 | N101: PROPOSÉ | O101: =IF(M101="","",M101-L101) | P101: =IF(OR(M101="",M101=0),"",(M101-L101)/M101) | Q101: =IF(OR(M101="",L101=0,L101=""),"",M101/L101) | R101: =IF(M101="","",M101*1.2)
A102: PROD-0414 | B102: Rhum botanique "Jardin à l'Anglaise" 70 cl 40° Nouveau design | C102: BOISSON_ALCOOLISEE | D102: SPIRITUEUX | E102: PREMIUM | F102: DISTILLERIE C'EST NOUS | G102: NORMAND DIRECT TERROIR | I102: 700 ml | J102: OUI | K102: 20 % | L102: 24.85 | M102: 37 | N102: PROPOSÉ | O102: =IF(M102="","",M102-L102) | P102: =IF(OR(M102="",M102=0),"",(M102-L102)/M102) | Q102: =IF(OR(M102="",L102=0,L102=""),"",M102/L102) | R102: =IF(M102="","",M102*1.2)
A103: PROD-0415 | B103: Rhum botanique "Le chaleureux" 70 cl 40° Nouveau design | C103: BOISSON_ALCOOLISEE | D103: SPIRITUEUX | E103: PREMIUM | F103: DISTILLERIE C'EST NOUS | G103: NORMAND DIRECT TERROIR | I103: 700 ml | J103: OUI | K103: 20 % | L103: 24.85 | M103: 37 | N103: PROPOSÉ | O103: =IF(M103="","",M103-L103) | P103: =IF(OR(M103="",M103=0),"",(M103-L103)/M103) | Q103: =IF(OR(M103="",L103=0,L103=""),"",M103/L103) | R103: =IF(M103="","",M103*1.2)
A104: PROD-0404 | B104: Gin 40° 70 cl Echantillon gratuit pour 6 sur demande | C104: BOISSON_ALCOOLISEE | D104: SPIRITUEUX | E104: PREMIUM | F104: DISTILLERIE C'EST NOUS | G104: NORMAND DIRECT TERROIR | I104: 700 ml | J104: OUI | K104: 20 % | L104: 23.25 | M104: 34.5 | N104: PROPOSÉ | O104: =IF(M104="","",M104-L104) | P104: =IF(OR(M104="",M104=0),"",(M104-L104)/M104) | Q104: =IF(OR(M104="",L104=0,L104=""),"",M104/L104) | R104: =IF(M104="","",M104*1.2)
...

Sheet Suivi
B1: Où en est la saisie
B3: Produits au total | C3: =COUNTA('Prix de vente'!A2:A703)
B4: Prix renseignés (proposés ou validés) | C4: =COUNT('Prix de vente'!M2:M703)
B5: Reste à saisir | C5: =C3-C4
B6: Avancement | C6: =IF(C3=0,0,C4/C3)
B7: Prix VALIDÉS par vous | C7: =COUNTIF('Prix de vente'!N2:N703,"VALIDÉ")
B8: Retenus au catalogue de saison | C8: =COUNTIF('Prix de vente'!S2:S703,"OUI")
B9: dont prix saisi | C9: =COUNTIFS('Prix de vente'!S2:S703,"OUI",'Prix de vente'!M2:M703,">0")
B10: reste à saisir sur la saison | C10: =C8-C9
B12: Contrôles
B14: Prix de vente ≤ prix d'achat | C14: =SUMPRODUCT(--('Prix de vente'!M2:M703<>""),--('Prix de vente'!M2:M703<='Prix de vente'!L2:L703))
B15: Taux de marge sous 30 % | C15: =SUMPRODUCT(--('Prix de vente'!M2:M703>0),--('Prix de vente'!P2:P703<0.3))
B16: TVA à confirmer | C16: =COUNTIF('Prix de vente'!K2:K703,"À CONFIRMER")
B17: dont déjà retenus en saison | C17: =COUNTIFS('Prix de vente'!K2:K703,"À CONFIRMER",'Prix de vente'!S2:S703,"OUI")
B19: Marge moyenne sur ce qui est saisi
B21: Taux de marge moyen | C21: =IFERROR(AVERAGEIF('Prix de vente'!M2:M703,">0",'Prix de vente'!P2:P703),"—")
B22: Coefficient moyen | C22: =IFERROR(AVERAGEIF('Prix de vente'!M2:M703,">0",'Prix de vente'!Q2:Q703),"—")
B24: Ces contrôles se mettent à jour tout seuls pendant la saisie. Une valeur non nulle sur les deux premiers demande une vérification.
